pandare/__init__.py
pandare/arch.py
pandare/asyncthread.py
pandare/cosi.py
pandare/panda.py
pandare/panda_expect.py
pandare/plog_pb2.py
pandare/plog_reader.py
pandare/pyplugin.py
pandare/pypluginmanager.py
pandare/qcows.json
pandare/qcows.py
pandare/qcows_internal.py
pandare/qemu_logging.py
pandare/utils.py
pandare/volatility_cli_classes.py
pandare/autogen/__init__.py
pandare/autogen/panda_aarch64_64.py
pandare/autogen/panda_arm_32.py
pandare/autogen/panda_datatypes.py
pandare/autogen/panda_i386_32.py
pandare/autogen/panda_mips64_64.py
pandare/autogen/panda_mips64el_64.py
pandare/autogen/panda_mips_32.py
pandare/autogen/panda_mipsel_32.py
pandare/autogen/panda_ppc_32.py
pandare/autogen/panda_ppc_64.py
pandare/autogen/panda_x86_64_64.py
pandare/data/pypanda/include/addr.h
pandare/data/pypanda/include/arm_helpers.h
pandare/data/pypanda/include/branch_meta.h
pandare/data/pypanda/include/breakpoints.h
pandare/data/pypanda/include/callstack_instr.h
pandare/data/pypanda/include/callstack_instr_int_fns.h
pandare/data/pypanda/include/callwitharg_int_fns.h
pandare/data/pypanda/include/callwitharg_ppp.h
pandare/data/pypanda/include/common.h
pandare/data/pypanda/include/cosi.h
pandare/data/pypanda/include/dynamic_symbols_int_fns.h
pandare/data/pypanda/include/exec-all.h
pandare/data/pypanda/include/forcedexec_int_fns.h
pandare/data/pypanda/include/forcedexec_ppp.h
pandare/data/pypanda/include/hooks2.h
pandare/data/pypanda/include/hooks2_ppp.h
pandare/data/pypanda/include/hooks_int_fns.h
pandare/data/pypanda/include/hw_proc_id_int_fns.h
pandare/data/pypanda/include/hypercaller.h
pandare/data/pypanda/include/libc_includes.h
pandare/data/pypanda/include/mem_hooks_int_fns.h
pandare/data/pypanda/include/os_intro.h
pandare/data/pypanda/include/osi_int_fns.h
pandare/data/pypanda/include/osi_linux_int_fns.h
pandare/data/pypanda/include/osi_types.h
pandare/data/pypanda/include/panda_datatypes.h
pandare/data/pypanda/include/panda_datatypes_ARM_32.h
pandare-1.8.82.dist-info/METADATA
pandare-1.8.82.dist-info/WHEEL
pandare-1.8.82.dist-info/top_level.txt
pandare-1.8.82.dist-info/RECORD
