Metadata-Version: 2.4
Name: pandare
Version: 1.8.82
Summary: Python Interface to PANDA
Home-page: https://github.com/panda-re/panda/
Author: Andrew Fasano, Tim Leek
Author-email: Luke Craig <luke.craig@mit.edu>
Requires-Python: >=3.6
Requires-Dist: cffi>=1.14.3
Requires-Dist: protobuf>=4.25.1
Requires-Dist: colorama
Dynamic: home-page
